testpack24/__init__.py
testpack24/cluster.py
testpack24/isochrones.py
testpack24/likelihood.py
testpack24/synthetic.py
testpack24/test_module.py~
testpack24-0.0.2.dist-info/METADATA
testpack24-0.0.2.dist-info/WHEEL
testpack24-0.0.2.dist-info/RECORD
